a3d_cli/__init__.py
a3d_cli/cli.py
a3d_cli/config.py
a3d_cli/dictparser.py
a3d_cli/exceptions.py
a3d_cli/interface.py
a3d_cli/order_params.py
a3d_cli-1.0.0.dist-info/entry_points.txt
a3d_cli-1.0.0.dist-info/LICENSE
a3d_cli-1.0.0.dist-info/WHEEL
a3d_cli-1.0.0.dist-info/METADATA
a3d_cli-1.0.0.dist-info/RECORD
