Metadata-Version: 2.1
Name: a3d-cli
Version: 1.0.0
Summary: Axial3D CLI
License: Apache-2.0
Author: Axial3D
Author-email: opensource@axial3d.com
Requires-Python: >=3.8,<4.0
Classifier: License :: OSI Approved :: Apache Software License
Classifier: Programming Language :: Python :: 3
Classifier: Programming Language :: Python :: 3.8
Classifier: Programming Language :: Python :: 3.9
Requires-Dist: python-dateutil (>=2.8.2,<3.0.0)
Requires-Dist: requests (>=2.26.0,<3.0.0)
